platform_lookup/__init__.py
platform_lookup/app.py
volttron_platform_lookup-0.1.0rc1.dist-info/LICENSE
volttron_platform_lookup-0.1.0rc1.dist-info/METADATA
volttron_platform_lookup-0.1.0rc1.dist-info/WHEEL
volttron_platform_lookup-0.1.0rc1.dist-info/entry_points.txt
volttron_platform_lookup-0.1.0rc1.dist-info/RECORD
