Metadata-Version: 2.3
Name: volttron-platform-lookup
Version: 0.1.0rc1
Summary: Web service that runs outside of VOLTTRON server and let VOLTTRON instance to register itself and lookup for services that can be part of a federated group
License: Apache-2.0
Author: volttron
Author-email: volttron@pnnl.gov
Requires-Python: >=3.9
Classifier: License :: OSI Approved :: Apache Software License
Classifier: Programming Language :: Python :: 3
Classifier: Programming Language :: Python :: 3.9
Classifier: Programming Language :: Python :: 3.10
Classifier: Programming Language :: Python :: 3.11
Classifier: Programming Language :: Python :: 3.12
Classifier: Programming Language :: Python :: 3.13
Requires-Dist: fastapi (>=0.118.0)
Requires-Dist: uvicorn (>=0.37.0)
Project-URL: Documentation, https://github.com/eclipse-volttron/platform-lookup
Project-URL: Repository, https://github.com/eclipse-volttron/platform-lookup
